[
  {
    "Type": "AkAssetPlatformData",
    "Name": "AkAssetPlatformData_0",
    "Outer": "AKE_Weapon_SphereLauncher_Launch",
    "Class": "UScriptClass'AkAssetPlatformData'"
  },
  {
    "Type": "AkAudioEvent",
    "Name": "AKE_Weapon_SphereLauncher_Launch",
    "Class": "UScriptClass'AkAudioEvent'",
    "Properties": {
      "PlatformAssetData": {
        "ObjectName": "AkAssetPlatformData'AKE_Weapon_SphereLauncher_Launch:AkAssetPlatformData_0'",
        "ObjectPath": "Pal/Content/Pal/Sound/Events/SE/Weapon/SphereLauncher/AKE_Weapon_SphereLauncher_Launch.0"
      },
      "ShortID": 1418602935
    }
  },
  {
    "Type": "AkAudioEventData",
    "Name": "AkAudioEventData_0",
    "Outer": "AKE_Weapon_SphereLauncher_Launch",
    "Class": "UScriptClass'AkAudioEventData'",
    "Properties": {
      "MaxAttenuationRadius": 8000.0,
      "MinimumDuration": 0.865,
      "MaximumDuration": 0.865,
      "UserDefinedSends": [
        {
          "ObjectName": "AkAuxBus'Cave_Reverb'",
          "ObjectPath": "Pal/Content/Pal/Sound/Master-Mixer_Hierarchy/Default_Work_Unit/Master_Audio_Bus/GlobalVolumeSetting/SE/Cave_Reverb/Cave_Reverb.2"
        }
      ],
      "MediaList": [
        {
          "ObjectName": "AkMediaAsset'815923457'",
          "ObjectPath": "Pal/Content/Pal/Sound/Media/815923457.0"
        }
      ],
      "CachedHash": 3132614555
    }
  }
]