[
  {
    "Type": "AkAssetPlatformData",
    "Name": "AkAssetPlatformData_0",
    "Outer": "AKE_Pal_Electric_01",
    "Class": "UScriptClass'AkAssetPlatformData'"
  },
  {
    "Type": "AkAudioEvent",
    "Name": "AKE_Pal_Electric_01",
    "Class": "UScriptClass'AkAudioEvent'",
    "Properties": {
      "RequiredBank": {
        "ObjectName": "AkAudioBank'AKB_SE_Pal'",
        "ObjectPath": "Pal/Content/Pal/Sound/SoundBank/AKB_SE_Pal.2"
      },
      "PlatformAssetData": {
        "ObjectName": "AkAssetPlatformData'AKE_Pal_Electric_01:AkAssetPlatformData_0'",
        "ObjectPath": "Pal/Content/Pal/Sound/Events/SE/Pal/Effect/AKE_Pal_Electric_01.0"
      },
      "ShortID": 376489024
    }
  },
  {
    "Type": "AkAudioEventData",
    "Name": "AkAudioEventData_0",
    "Outer": "AKE_Pal_Electric_01",
    "Class": "UScriptClass'AkAudioEventData'",
    "Properties": {
      "MaxAttenuationRadius": 2000.0,
      "IsInfinite": true,
      "MediaList": [
        {
          "ObjectName": "AkMediaAsset'308142199'",
          "ObjectPath": "Pal/Content/Pal/Sound/Media/308142199.0"
        }
      ]
    }
  }
]